{
  "users": [
    {
      "id": "1",
      "username": "testuser",
      "password": "password123"
    },
    {
      "id": "2",
      "username": "rado",
      "password": "rado123"
    },
    {
      "id": "3",
      "username": "teacher",
      "password": "teacher123"
    },
    {
      "id": "3",
      "username": "test",
      "password": "test123"
    }
  ],
  "shoppinglist": [
    {
      "id": "42c6",
      "name": "terst 123",
      "quantity": 1
    },
    {
      "id": "d5ff",
      "name": "Milk",
      "quantity": 3
    },
    {
      "id": "e2ce",
      "name": "teqteq",
      "quantity": 1
    }
  ]
}