{
  "users": [
    {
      "id": "1",
      "username": "testuser",
      "password": "password123"
    },
    {
      "id": "2",
      "username": "rado",
      "password": "rado123"
    },
    {
      "id": "3",
      "username": "teacher",
      "password": "teacher123"
    },
    {
      "id": "6023",
      "username": "kvostava",
      "email": "kvostava@abv.bg",
      "password": "12345678"
    },
    {
      "id": "d381",
      "username": "kvostava",
      "email": "kvostava@abv.bg",
      "password": "1"
    },
    {
      "id": "367d",
      "username": "test",
      "email": "test@abv.bg",
      "password": "test1234"
    }
  ],
  "shoppinglist": []
}